pytest_relay_ws/__init__.py
pytest_relay_ws/observer.py
pytest_relay_ws/plugin.py
pytest_relay_ws/py.typed
pytest_relay_ws-0.0.1.dist-info/METADATA
pytest_relay_ws-0.0.1.dist-info/WHEEL
pytest_relay_ws-0.0.1.dist-info/entry_points.txt
pytest_relay_ws-0.0.1.dist-info/licenses/COPYING
pytest_relay_ws-0.0.1.dist-info/RECORD
